<?xml version="1.0"?>
<menu>
  <item>
    <path>civicrm/booking/add</path>
    <page_callback>CRM_Civibooking_Form_Booking</page_callback>
    <title>Booking</title>
    <access_arguments>access CiviCRM</access_arguments>
  </item>
  <item>
    <path>civicrm/booking/tab</path>
    <page_callback>CRM_Civibooking_Page_Tab</page_callback>
    <title>Tab</title>
    <access_arguments>access CiviCRM</access_arguments>
  </item>
  <item>
    <path>civicrm/booking/dashboard</path>
    <page_callback>CRM_Civibooking_Page_Dashboard</page_callback>
    <title>Dashboard</title>
    <access_arguments>access CiviCRM</access_arguments>
  </item>
</menu>
